odoo/addons/ssi_project_template/README.rst
odoo/addons/ssi_project_template/__init__.py
odoo/addons/ssi_project_template/__manifest__.py
odoo/addons/ssi_project_template/demo/project_template_demo.xml
odoo/addons/ssi_project_template/demo/task_template_demo.xml
odoo/addons/ssi_project_template/models/__init__.py
odoo/addons/ssi_project_template/models/project_project.py
odoo/addons/ssi_project_template/models/project_task.py
odoo/addons/ssi_project_template/models/project_template.py
odoo/addons/ssi_project_template/models/task_template.py
odoo/addons/ssi_project_template/security/ir.model.access.csv
odoo/addons/ssi_project_template/security/res_group_data.xml
odoo/addons/ssi_project_template/static/description/icon.png
odoo/addons/ssi_project_template/views/project_project_views.xml
odoo/addons/ssi_project_template/views/project_task_views.xml
odoo/addons/ssi_project_template/views/project_template_views.xml
odoo/addons/ssi_project_template/views/task_template_views.xml
odoo14_addon_ssi_project_template-14.0.2.0.0.dist-info/METADATA
odoo14_addon_ssi_project_template-14.0.2.0.0.dist-info/WHEEL
odoo14_addon_ssi_project_template-14.0.2.0.0.dist-info/top_level.txt
odoo14_addon_ssi_project_template-14.0.2.0.0.dist-info/RECORD
